



<web-app>
    <!-- 配置Shiro的SecurityManager -->
    <bean id="securityManager" class="org.apache.shiro.web.mgt.DefaultWebSecurityManager">
        <property name="realm" ref="userRealm"/>
        <property name="cacheManager" ref="cacheManager"/>
        <property name="sessionManager" ref="sessionManager"/>
        <property name="rememberMeManager" ref="rememberMeManager"/>
    </bean>
    <!-- rememberMeCookie -->
    <bean id="rememberMeCookie" class="org.apache.shiro.web.servlet.SimpleCookie">
        <constructor-arg value="rememberMe"/>
        <property name="httpOnly" value="true"/>
        <property name="maxAge" value="2592000"/> <!-- 调整超时时间 -->
    </bean>
    <!-- rememberMe管理器 -->
    <bean id="rememberMeManager" class="org.apache.shiro.web.mgt.CookieRememberMeManager">
        <property name="cookie" ref="rememberMeCookie"/>
    </bean>
</web-app>